{"students":[{"degree":"BA","year":1,"rectorExcellence":false,"courses":["Te9402383733SMHa"],"firstName":"Niv","lastName":"Kaufman","email":"rmail@gmail.com","password":"123123","id":"2Z26iMY1618iKe37","type":"Student","tz":"3112","activation":true,"level":100},{"degree":"Bsc","year":0,"rectorExcellence":false,"courses":["Te9402383733SMHa"],"firstName":"Or","lastName":"Bar","email":"asd@asd","password":"password","id":"8e25I7p3BG007DU4","type":"Student","tz":"311328","activation":false,"level":0}],"grades":[{"courseID":"Te9402383733SMHa","studentID":"8e25I7p3BG007DU4","id":"_2t0PW8iA7bNqc69","zion":90.0,"percentage":30.0,"title":"Test-1"}],"courses":[{"id":"Te9402383733SMHa","name":"Infi","num":101,"studentsAmount":20,"status":true,"studentsIDs":["8e25I7p3BG007DU4","2Z26iMY1618iKe37"],"teachersIDs":["7WB7cq1tFh9f9L75"]}],"teachers":[{"courses":[],"firstName":"Noy","lastName":"S","email":"2","password":"123","id":"QS6qq95J0`TEifR6","type":"Teacher","tz":"311","activation":false,"level":0},{"courses":["Te9402383733SMHa"],"firstName":"Noy","lastName":"S","email":"Noy@gmail.com","password":"password1","id":"7WB7cq1tFh9f9L75","type":"Teacher","tz":"311","activation":false,"level":0}]}